functionalpy/__init__.py
functionalpy/_sequence.py
functionalpy/_sequence.pyi
functionalpy/py.typed
functionalpy/test_sequence.py
functionalpy/benchmark/utils.py
functionalpy/benchmark/query_1/input_data.py
functionalpy/benchmark/query_1/iterators_q1.py
functionalpy/benchmark/query_1/polars_q1.py
functionalpy-0.17.0.dist-info/LICENSE
functionalpy-0.17.0.dist-info/METADATA
functionalpy-0.17.0.dist-info/WHEEL
functionalpy-0.17.0.dist-info/top_level.txt
functionalpy-0.17.0.dist-info/RECORD
