Metadata-Version: 2.1
Name: functionalpy
Version: 0.17.0
Summary: functionalpy
Author-email: Martin Bernstorff <martinbernstorff@gmail.com>
License: MIT License
Project-URL: homepage, https://github.com/MartinBernstorff/FunctionalPy
Project-URL: repository, https://github.com/MartinBernstorff/FunctionalPy
Project-URL: documentation, https://MartinBernstorff.github.io/FunctionalPy/
Classifier: Programming Language :: Python :: 3.10
Classifier: Programming Language :: Python :: 3.11
Requires-Python: >=3.10
License-File: LICENSE
Requires-Dist: linetimer
Requires-Dist: polars
Provides-Extra: dev
Requires-Dist: cruft ==2.15.0 ; extra == 'dev'
Requires-Dist: pyright ==1.1.344 ; extra == 'dev'
Requires-Dist: pytest ==7.4.4 ; extra == 'dev'
Requires-Dist: pytest-cov ==4.1.0 ; extra == 'dev'
Requires-Dist: pytest-xdist ==3.5.0 ; extra == 'dev'
Requires-Dist: pytest-sugar ==0.9.7 ; extra == 'dev'
Requires-Dist: diff-cover ==8.0.2 ; extra == 'dev'
Requires-Dist: ruff ==0.1.9 ; extra == 'dev'
